orlang/__init__.py
orlang/cli.py
orlang/grammar.lark
orlang/parser.py
orlang/runner.py
orlang/transpiler.py
orlang-0.1.1.dist-info/licenses/LICENSE
orlang-0.1.1.dist-info/METADATA
orlang-0.1.1.dist-info/WHEEL
orlang-0.1.1.dist-info/entry_points.txt
orlang-0.1.1.dist-info/top_level.txt
orlang-0.1.1.dist-info/RECORD
