Metadata-Version: 2.4
Name: orlang
Version: 0.1.1
Summary: A simple, expressive programming language that transpiles to Python
Author-email: Firomsa Assefa <firomsassf@gmail.com>
License: MIT
Classifier: Development Status :: 3 - Alpha
Classifier: Intended Audience :: Developers
Classifier: License :: OSI Approved :: MIT License
Classifier: Programming Language :: Python :: 3
Classifier: Programming Language :: Python :: 3.13
Classifier: Topic :: Software Development :: Compilers
Requires-Python: >=3.13
License-File: LICENSE
Requires-Dist: lark>=1.2.2
Dynamic: license-file
